{"skeleton":{"hash":"1lv+ybYnfng","spine":"4.2.43","x":-1291.45,"y":-998.13,"width":2260.26,"height":1821.61,"images":"../Desktop/새 폴더 (2)/이미지파일/비스킷버그/","audio":"./audio"},"bones":[{"name":"root","scaleX":-0.98},{"name":"body","parent":"root","length":528.33,"rotation":-62.48,"x":-106.18,"y":496.61},{"name":"head","parent":"body","length":817.41,"rotation":-5.37,"x":517.3,"y":0.18},{"name":"wing-r1","parent":"body","length":511.61,"rotation":129.5,"x":583.66,"y":107.42},{"name":"wing-r2","parent":"body","length":258.46,"rotation":77.97,"x":665.47,"y":220.51},{"name":"wing-l1","parent":"body","length":582.89,"rotation":-141.48,"x":533.82,"y":-133.55},{"name":"wing-l2","parent":"body","length":475.38,"rotation":-90.03,"x":531.85,"y":-187.36},{"name":"body2","parent":"body","x":495.49,"y":-0.77}],"slots":[{"name":"비스킷버그 몸통","bone":"body2","attachment":"비스킷버그 몸통"},{"name":"비스킷버그 오른날개2","bone":"wing-r2","attachment":"비스킷버그 오른날개2"},{"name":"비스킷버그 오른날개1","bone":"wing-r1","attachment":"비스킷버그 오른날개1"},{"name":"비스킷버그 왼날개2","bone":"wing-l2","attachment":"비스킷버그 왼날개2"},{"name":"비스킷버그 왼날개1","bone":"wing-l1","attachment":"비스킷버그 왼날개1"},{"name":"비스킷버그 머리","bone":"head","attachment":"비스킷버그 머리"}],"skins":[{"name":"default","attachments":{"비스킷버그 머리":{"비스킷버그 머리":{"x":151.62,"y":-37.48,"rotation":67.85,"width":2210,"height":1763}},"비스킷버그 몸통":{"비스킷버그 몸통":{"x":119.36,"y":-30.05,"rotation":62.48,"width":2210,"height":1763}},"비스킷버그 오른날개1":{"비스킷버그 오른날개1":{"x":-182.71,"y":71.86,"rotation":-67.02,"width":2210,"height":1763}},"비스킷버그 오른날개2":{"비스킷버그 오른날개2":{"x":-288.01,"y":10.98,"rotation":-15.49,"width":2210,"height":1763}},"비스킷버그 왼날개1":{"비스킷버그 왼날개1":{"x":-163.58,"y":-8.59,"rotation":-156.04,"width":2210,"height":1763}},"비스킷버그 왼날개2":{"비스킷버그 왼날개2":{"x":-192.14,"y":149.31,"rotation":152.5,"width":2210,"height":1763}}}}],"animations":{"dead":{"slots":{"비스킷버그 머리":{"rgba":[{"time":1.1667,"color":"ffffffff"},{"time":1.8333,"color":"ffffff00"}]},"비스킷버그 몸통":{"rgba":[{"time":1.1667,"color":"ffffffff"},{"time":1.8333,"color":"ffffff00"}]},"비스킷버그 오른날개1":{"rgba":[{"time":1.1667,"color":"ffffffff"},{"time":1.8333,"color":"ffffff00"}]},"비스킷버그 오른날개2":{"rgba":[{"time":1.1667,"color":"ffffffff"},{"time":1.8333,"color":"ffffff00"}]},"비스킷버그 왼날개1":{"rgba":[{"time":1.1667,"color":"ffffffff"},{"time":1.8333,"color":"ffffff00"}]},"비스킷버그 왼날개2":{"rgba":[{"time":1.1667,"color":"ffffffff"},{"time":1.8333,"color":"ffffff00"}]}},"bones":{"head":{"rotate":[{},{"time":0.1,"value":9.1},{"time":0.2,"value":-1.13},{"time":0.3,"value":9.1},{"time":0.4,"value":-1.13,"curve":"stepped"},{"time":0.6667,"value":-1.13,"curve":[1,-1.13,1,47.68]},{"time":1,"value":47.68}],"translate":[{"time":0.6667,"curve":[1,0,1,5.3,1,0,1,-156.2]},{"time":1,"x":5.3,"y":-156.2}]},"wing-l1":{"rotate":[{},{"time":0.1,"value":-11.1},{"time":0.2,"value":2.57},{"time":0.3,"value":-11.1},{"time":0.4,"value":2.57,"curve":"stepped"},{"time":0.6667,"value":2.57,"curve":[1,2.57,1,35.07]},{"time":1,"value":35.07}]},"wing-l2":{"rotate":[{},{"time":0.1,"value":8.28},{"time":0.2,"value":-6.29},{"time":0.3,"value":8.28},{"time":0.4,"value":-6.29,"curve":"stepped"},{"time":0.6667,"value":-6.29,"curve":[1,-6.29,1,29.22]},{"time":1,"value":29.22}]},"wing-r1":{"rotate":[{},{"time":0.1,"value":19.24},{"time":0.2,"value":-5.86},{"time":0.3,"value":19.24},{"time":0.4,"value":-5.86,"curve":"stepped"},{"time":0.6667,"value":-5.86,"curve":[1,-5.86,1,-73.53]},{"time":1,"value":-73.53}]},"wing-r2":{"rotate":[{},{"time":0.1,"value":-17.07},{"time":0.2,"value":12.03},{"time":0.3,"value":-17.07},{"time":0.4,"value":12.03,"curve":"stepped"},{"time":0.6667,"value":12.03,"curve":[1,12.03,1,-53.39]},{"time":1,"value":-53.39}]},"body":{"rotate":[{},{"time":0.1,"value":-4.86},{"time":0.2,"value":2.02},{"time":0.3,"value":-4.86},{"time":0.4,"value":2.02}],"translate":[{"time":0.6667,"curve":[1,0,1,0,1,0,1,-1267.99]},{"time":1,"y":-1267.99}]}}},"move":{"bones":{"body":{"translate":[{"curve":[0.125,0,0.375,0,0.125,0,0.375,-91.24]},{"time":0.5,"y":-91.24,"curve":[0.625,0,0.875,0,0.625,-91.24,0.875,0]},{"time":1}]},"wing-l1":{"rotate":[{"value":-23},{"time":0.1667,"value":24.95},{"time":0.3333,"value":-23},{"time":0.5,"value":24.95},{"time":0.6667,"value":-23},{"time":0.8333,"value":24.95},{"time":1,"value":-23}]},"wing-r1":{"rotate":[{"value":23.79},{"time":0.1667,"value":-35.42},{"time":0.3333,"value":23.79},{"time":0.5,"value":-35.42},{"time":0.6667,"value":23.79},{"time":0.8333,"value":-35.42},{"time":1,"value":23.79}]},"wing-l2":{"rotate":[{"value":-23.11},{"time":0.1,"value":11.24},{"time":0.2,"value":-23.11},{"time":0.3,"value":11.24},{"time":0.4,"value":-23.11},{"time":0.5,"value":11.24},{"time":0.6,"value":-23.11},{"time":0.7,"value":11.24},{"time":0.8,"value":-23.11},{"time":0.9,"value":11.24},{"time":1,"value":-23.11}]},"wing-r2":{"rotate":[{"value":30.79},{"time":0.1,"value":-26.43},{"time":0.2,"value":30.79},{"time":0.3,"value":-26.43},{"time":0.4,"value":30.79},{"time":0.5,"value":-26.43},{"time":0.6,"value":30.79},{"time":0.7,"value":-26.43},{"time":0.8,"value":30.79},{"time":0.9,"value":-26.43},{"time":1,"value":30.79}]},"head":{"rotate":[{"value":-5.88,"curve":[0.5,-5.88,0,-2.44]},{"time":0.5,"value":-2.44,"curve":[0.733,-2.44,0.5,-9.02]},{"time":0.7333,"value":-9.02,"curve":[1,-9.02,0.76,-5.88]},{"time":1,"value":-5.88}]},"body2":{"rotate":[{},{"time":0.3333,"value":-11.01},{"time":0.6667,"value":5.54},{"time":1}]}}}}}